mplstereonet/__init__.py
mplstereonet/analysis.py
mplstereonet/contouring.py
mplstereonet/convenience_functions.py
mplstereonet/stereonet_axes.py
mplstereonet/stereonet_math.py
mplstereonet/stereonet_transforms.py
mplstereonet/utilities.py
mplstereonet-0.6.2.dist-info/LICENSE
mplstereonet-0.6.2.dist-info/METADATA
mplstereonet-0.6.2.dist-info/WHEEL
mplstereonet-0.6.2.dist-info/top_level.txt
mplstereonet-0.6.2.dist-info/RECORD
