Metadata-Version: 2.1
Name: mplstereonet
Version: 0.6.2
Summary: Stereonets for matplotlib
Home-page: https://github.com/joferkington/mplstereonet/
Author: Joe Kington
Author-email: joferkington@gmail.com
License: MIT
Platform: UNKNOWN
